justunits.py
justunits-0.2a2.dist-info/LICENSE.md
justunits-0.2a2.dist-info/METADATA
justunits-0.2a2.dist-info/WHEEL
justunits-0.2a2.dist-info/top_level.txt
justunits-0.2a2.dist-info/RECORD
