Metadata-Version: 2.1
Name: justunits
Version: 0.2a2
Summary: Handling unit specifications in strings.
Home-page: https://https://gitlab.com/david.scheliga/justunits
Author: David Scheliga
License: GNU General Public License V3 (GPLv3)
Project-URL: Documentation, https://justunits.readthedocs.io/en/latest/
Project-URL: Source Code Repository, https://https://gitlab.com/david.scheliga/justunits
Platform: UNKNOWN
Classifier: Development Status :: 3 - Alpha
Classifier: License :: OSI Approved :: GNU General Public License v3 (GPLv3)
Classifier: Operating System :: OS Independent
Classifier: Programming Language :: Python :: 3
Classifier: Programming Language :: Python :: 3.6
Classifier: Programming Language :: Python :: 3.7
Classifier: Programming Language :: Python :: 3.8
Classifier: Programming Language :: Python :: 3.9
